mlatom/EEEDDDD.py
mlatom/EEEDDDD_descriptor.py
mlatom/EEEDDDD_nn.py
mlatom/GICnet.py
mlatom/MLTPA.py
mlatom/ML_NEA.py
mlatom/MLatom.py
mlatom/MLatomF
mlatom/MLtasks.py
mlatom/__init__.py
mlatom/aiqm1.py
mlatom/aiqm2.py
mlatom/al.py
mlatom/al_utils.py
mlatom/args_class.py
mlatom/ccsdtstarcbs.py
mlatom/ciopt.py
mlatom/composite_methods.py
mlatom/constants.py
mlatom/conversions.py
mlatom/cs.so
mlatom/data.py
mlatom/decorators.py
mlatom/dens.py
mlatom/doc.py
mlatom/functionsGICnet.py
mlatom/gap_md.py
mlatom/gen_ts_methods.py
mlatom/header.py
mlatom/initial_conditions.py
mlatom/interface_MLatomF.py
mlatom/irc.py
mlatom/kreg_api.py
mlatom/krr_julia.py
mlatom/log.py
mlatom/md.py
mlatom/md2vibr.py
mlatom/md2vibr_cmd.py
mlatom/md_cmd.py
mlatom/md_parallel.py
mlatom/mlatom_gui.py
mlatom/model_cls.py
mlatom/models.py
mlatom/namd.py
mlatom/omnip1.py
mlatom/omnip1_nn.py
mlatom/plot.py
mlatom/ref.json
mlatom/shell_cmd.py
mlatom/simulations.py
mlatom/sliceData.py
mlatom/spectra.py
mlatom/stats.py
mlatom/stopper.py
mlatom/thermostat.py
mlatom/utils.py
mlatom/xyz.py
mlatom/MLatomF_src/A_KRR.f90
mlatom/MLatomF_src/A_KRR_kernel.f90
mlatom/MLatomF_src/D_CoulombMatrix.f90
mlatom/MLatomF_src/D_ID.f90
mlatom/MLatomF_src/D_rel2eq.f90
mlatom/MLatomF_src/MLatomF.f90
mlatom/MLatomF_src/MLatomFInfo.f90
mlatom/MLatomF_src/MLmodel.f90
mlatom/MLatomF_src/Makefile
mlatom/MLatomF_src/Makefile.intel
mlatom/MLatomF_src/__init__.py
mlatom/MLatomF_src/analyze.f90
mlatom/MLatomF_src/constants.f90
mlatom/MLatomF_src/cs.cpp
mlatom/MLatomF_src/dataset.f90
mlatom/MLatomF_src/mathUtils.f90
mlatom/MLatomF_src/molDescr.f90
mlatom/MLatomF_src/optionsModule.f90
mlatom/MLatomF_src/precision.f90
mlatom/MLatomF_src/recover.sh
mlatom/MLatomF_src/sampling.f90
mlatom/MLatomF_src/statistics.f90
mlatom/MLatomF_src/stopper.f90
mlatom/MLatomF_src/strings.f90
mlatom/MLatomF_src/timing.f90
mlatom/MLatomF_src/types.f90
mlatom/addons/__init__.py
mlatom/addons/aiqm3/__init__.py
mlatom/addons/aiqm3/aiqm3.py
mlatom-3.20.0.dist-info/LICENSE.txt
mlatom-3.20.0.dist-info/METADATA
mlatom-3.20.0.dist-info/WHEEL
mlatom-3.20.0.dist-info/entry_points.txt
mlatom-3.20.0.dist-info/top_level.txt
mlatom-3.20.0.dist-info/RECORD
