Metadata-Version: 2.1
Name: mlatom
Version: 3.20.0
Summary: A Package for AI-enhanced computational chemistry
Home-page: http://mlatom.com
Author: Pavlo O. Dral
Author-email: admin@mlatom.com
License: MIT (modified)
Classifier: Programming Language :: Python :: 3
Classifier: Operating System :: POSIX :: Linux
Classifier: Programming Language :: Fortran
Classifier: Topic :: Scientific/Engineering :: Chemistry
Classifier: Environment :: Console
Requires-Python: >=3.8
License-File: LICENSE.txt
Requires-Dist: numpy
Requires-Dist: scipy
Requires-Dist: h5py
Requires-Dist: pyh5md
Requires-Dist: torch
Requires-Dist: torchani
Requires-Dist: matplotlib
Requires-Dist: statsmodels
Requires-Dist: tqdm
